deeptl/__init__.py
deeptl/_data_fusion.py
deeptl/_version.py
deeptl/clustering/__init__.py
deeptl/clustering/_dcl.py
deeptl/clustering/_dtc.py
test/__init__.py
test/test_dtl.py
deeptl-1.0.0.dist-info/LICENSE.txt
deeptl-1.0.0.dist-info/METADATA
deeptl-1.0.0.dist-info/WHEEL
deeptl-1.0.0.dist-info/top_level.txt
deeptl-1.0.0.dist-info/RECORD
